yasiu_vis/__init__.py
yasiu_vis/ykeras.py
yasiu_vis/ypandas.py
yasiu_vis-0.6.1.dist-info/LICENSE
yasiu_vis-0.6.1.dist-info/METADATA
yasiu_vis-0.6.1.dist-info/WHEEL
yasiu_vis-0.6.1.dist-info/top_level.txt
yasiu_vis-0.6.1.dist-info/RECORD
