Metadata-Version: 2.1
Name: yasiu-vis
Version: 0.6.1
Summary: High level visualisation for pandas and keras, based on matplotlib
Author: Grzegorz Krug
Author-email: kruggrzegorz@gmail.com
Maintainer: Grzegorz Krug
Maintainer-email: kruggrzegorz@gmail.com
License: MIT
Project-URL: 1. Native Package, https://pypi.org/project/yasiu-native/
Project-URL: 2. Math Package, https://pypi.org/project/yasiu-math/
Project-URL: 3. Image Package, https://pypi.org/project/yasiu-image/
Project-URL: 4. Visualisation Package, https://pypi.org/project/yasiu-vis/
Project-URL: 5. Source Code, https://github.com/GrzegorzKrug/yasiu-vis
Keywords: numpy,matplotlib,pandas,visualisation,dataframe,pyplot,keras,tensorflow
Classifier: Development Status :: 5 - Production/Stable
Classifier: Programming Language :: Python :: 3
Classifier: Programming Language :: Python :: 3.7
Classifier: Programming Language :: Python :: 3.8
Classifier: Programming Language :: Python :: 3.9
Classifier: Programming Language :: Python :: 3.10
Classifier: Programming Language :: Python :: 3.11
Classifier: Programming Language :: Python :: Implementation :: CPython
Classifier: Topic :: Scientific/Engineering :: Mathematics
Classifier: Topic :: Scientific/Engineering :: Visualization
Classifier: Framework :: Matplotlib
Classifier: Intended Audience :: Education
Classifier: Intended Audience :: Developers
Classifier: Intended Audience :: Science/Research
Classifier: License :: OSI Approved :: MIT License
Classifier: Operating System :: OS Independent
Requires-Python: >=3.7
License-File: LICENSE
Requires-Dist: matplotlib
Requires-Dist: yasiu-math
Requires-Dist: numpy
